bot/__init__.py
bot/base_operator_checker.py
bot/config_parser.py
bot/guideline_parser.py
bot/operator_detection.py
bot/utils.py
bot/arithmetic/__init__.py
bot/arithmetic/arithmetic_checker.py
bot/bitwise/__init__.py
bot/bitwise/bitwise_checker.py
bot/comparison/__init__.py
bot/comparison/comparison_checker.py
bot/identity_membership/__init__.py
bot/identity_membership/identity_checker.py
bot/identity_membership/membership_checker.py
bot/logical/__init__.py
bot/logical/logical_checker.py
PyGCA-1.0.1.dist-info/LICENSE
PyGCA-1.0.1.dist-info/METADATA
PyGCA-1.0.1.dist-info/WHEEL
PyGCA-1.0.1.dist-info/top_level.txt
PyGCA-1.0.1.dist-info/RECORD
