Metadata-Version: 2.1
Name: PyGCA
Version: 1.0.1
Summary: A tool for detecting and analyzing Python operators like arithmetic, bitwise, comparison, and more.
Home-page: https://github.com/clintaire/PyGCA
Author: Clintaire
Author-email: clintaire@gmail.com
Classifier: Programming Language :: Python :: 3
Classifier: License :: OSI Approved :: MIT License
Classifier: Operating System :: OS Independent
Requires-Python: >=3.7
License-File: LICENSE
Requires-Dist: Deprecated==1.2.14
Requires-Dist: Jinja2==3.1.4
Requires-Dist: MarkupSafe==2.1.5
Requires-Dist: PyGithub==2.4.0
Requires-Dist: PyJWT==2.9.0
Requires-Dist: PyNaCl==1.5.0
Requires-Dist: certifi==2024.8.30
Requires-Dist: cffi==1.17.1
Requires-Dist: charset-normalizer==3.3.2
Requires-Dist: cryptography==43.0.1
Requires-Dist: idna==3.10
Requires-Dist: iniconfig==2.0.0
Requires-Dist: packaging==24.1
Requires-Dist: pluggy==1.5.0
Requires-Dist: pycparser==2.22
Requires-Dist: pytest==8.3.3
Requires-Dist: requests==2.32.3
Requires-Dist: typing-extensions==4.12.2
Requires-Dist: urllib3==2.2.3
Requires-Dist: wrapt==1.16.0
